ollamac/__init__.py
ollamac/__main__.py
ollamac/ollamac.py
ollamac-0.1.2.dist-info/entry_points.txt
ollamac-0.1.2.dist-info/METADATA
ollamac-0.1.2.dist-info/WHEEL
ollamac-0.1.2.dist-info/RECORD
