Metadata-Version: 2.1
Name: ollamac
Version: 0.1.2
Summary: 
License: Apache-2.0
Keywords: ollama,command line interface
Author: Promotos
Author-email: promotos@gmx.de
Requires-Python: >=3.10,<4.0
Classifier: Development Status :: 3 - Alpha
Classifier: License :: OSI Approved :: Apache Software License
Classifier: Natural Language :: English
Classifier: Operating System :: OS Independent
Classifier: Programming Language :: Python
Classifier: Programming Language :: Python :: 3
Classifier: Programming Language :: Python :: 3.10
Classifier: Programming Language :: Python :: 3.11
Requires-Dist: argparse (>=1.4.0,<2.0.0)
Requires-Dist: requests (>=2.31.0,<3.0.0)
